zdev/__init__.py
zdev/colors.py
zdev/core.py
zdev/display.py
zdev/indexing.py
zdev/parallel.py
zdev/searchstr.py
zdev/sound.py
zdev/testing.py
zdev/utils.py
zdev/validio.py
zdev-0.2.1.dist-info/licenses/LICENSE
zdev-0.2.1.dist-info/METADATA
zdev-0.2.1.dist-info/WHEEL
zdev-0.2.1.dist-info/entry_points.txt
zdev-0.2.1.dist-info/top_level.txt
zdev-0.2.1.dist-info/RECORD
