Metadata-Version: 2.4
Name: zdev
Version: 0.2.1
Summary: Versatile collection of helper functions for common development tasks
Author-email: "Dr. Marcus Zeller" <dsp4444@gmail.com>
License-Expression: GPL-3.0-or-later
Project-URL: Homepage, https://github.com/zynt3c/zdev
Project-URL: Package, https://pypi.org/project/zdev
Keywords: development,utilities,helpers
Requires-Python: >=3.12
License-File: LICENSE
Requires-Dist: matplotlib~=3.10.8
Requires-Dist: numpy~=2.4.1
Requires-Dist: plotly~=6.5.2
Requires-Dist: sounddevice~=0.5.5
Requires-Dist: zynamon
Dynamic: license-file
